coto/__init__.py
coto/captcha/__init__.py
coto/captcha/iterm_solver.py
coto/clients/__init__.py
coto/clients/account.py
coto/clients/billing.py
coto/clients/federation.py
coto/clients/iam.py
coto/clients/mfa.py
coto/clients/resetpassword.py
coto/clients/support.py
coto/clients/signin/__init__.py
coto/clients/signin_amazon/__init__.py
coto/clients/signin_aws/__init__.py
coto/clients/signin_aws/captcha_guess.py
coto/clients/signin_aws/exceptions.py
coto/metadata1/__init__.py
coto/metadata1/static_generator.py
coto/session/__init__.py
coto/session/session.py
tests/__init__.py
tests/clients/__init__.py
tests/session/__init__.py
tests/session/test_session.py
coto-0.4.0.dist-info/LICENSE.txt
coto-0.4.0.dist-info/METADATA
coto-0.4.0.dist-info/WHEEL
coto-0.4.0.dist-info/top_level.txt
coto-0.4.0.dist-info/RECORD
