Metadata-Version: 2.1
Name: coto
Version: 0.4.0
Summary: Undocumented AWS Mananagement Console API Client
Home-page: https://github.com/sentialabs/coto
Author: Sentia MPC B.V.
Author-email: info@sentia.com
License: Apache
Project-URL: Source, https://github.com/sentialabs/coto
Project-URL: Documentation, http://coto.readthedocs.io/
Keywords: aws boto
Platform: UNKNOWN
Classifier: Development Status :: 3 - Alpha
Classifier: Intended Audience :: Developers
Classifier: Intended Audience :: System Administrators
Classifier: License :: OSI Approved :: Apache Software License
Classifier: Programming Language :: Python :: 3 :: Only
Requires-Dist: ansicolors (==1.1.8)
Requires-Dist: appdirs (==1.4.4)
Requires-Dist: beautifulsoup4 (==4.9.3)
Requires-Dist: botocore (==1.23.23)
Requires-Dist: certifi (==2020.12.5)
Requires-Dist: chardet (==4.0.0)
Requires-Dist: distlib (==0.3.1)
Requires-Dist: filelock (==3.0.12)
Requires-Dist: furl (==2.1.0)
Requires-Dist: idna (==2.10)
Requires-Dist: jmespath (==0.10.0)
Requires-Dist: orderedmultidict (==1.0.1)
Requires-Dist: pyotp (==2.5.1)
Requires-Dist: python-dateutil (==2.8.1)
Requires-Dist: requests (==2.25.1)
Requires-Dist: six (==1.15.0)
Requires-Dist: soupsieve (==2.1)
Requires-Dist: urllib3 (==1.26.3)
Requires-Dist: Pillow (==8.4.0)
